ipbec
